{"name":"Projects1-4-sdi","body":" <!DOCTYPE html>\r\n<html>\r\n<head>\r\n  <meta charset='utf-8'>\r\n\r\n  <center>\r\n  <title>KBarrow/Projects1-4-Sdi.git</title>\r\n  </center> <style type=\"text/css\">\r\n    body {\r\n      margin-top: 1.0em;\r\n      background-color: #6698FF;\r\n      font-family: Helvetica, Arial, FreeSans, san-serif;\r\n      color: #000000;\r\n    }\r\n    #container {\r\n      margin: 0 auto;\r\n      width: 700px;\r\n    }\r\n    h1 { font-size: 3.8em; color: #000000; margin-bottom: 3px; }\r\n    h1 .small { font-size: 0.4em; }\r\n    h1 a { text-decoration: none }\r\n    h2 { font-size: 1.5em; color: #000000; }\r\n    h3 { text-align: center; color: #000000; }\r\n    a { color: #000000; }\r\n    .description { font-size: 1.2em; margin-bottom: 30px; margin-top: 30px; font-style: italic;}\r\n    .download { float: right; }\r\n    pre { background: #000; color: #fff; padding: 15px;}\r\n    hr { border: 0; width: 80%; border-bottom: 1px solid #aaa}\r\n    .footer { text-align:center; padding-top:30px; font-style: italic; }\r\n  </style>\r\n</head>\r\n\r\n<body>\r\n  <a href=\"https://github.com/KBarrow/SDI-Projects\"><img style=\"position: absolute; top: 0; right: 0; border: 0;\" src=\"http://s3.amazonaws.com/github/ribbons/forkme_right_darkblue_121621.png\" alt=\"Fork me on GitHub\" /></a>\r\n\r\n  <div id=\"container\">\r\n\r\n    <div class=\"download\">\r\n      <a href=\"https://github.com/KBarrow/SDI-Projects/zipball/master\">\r\n        <img border=\"0\" width=\"90\" src=\"https://github.com/images/modules/download/zip.png\"></a>\r\n      <a href=\"https://github.com/KBarrow/SDI-Projects/tarball/master\">\r\n        <img border=\"0\" width=\"90\" src=\"https://github.com/images/modules/download/tar.png\"></a>\r\n    </div>\r\n\r\n    <h1><a href=\"https://github.com/KBarrow/SDI-Projects\">SDI-Projects</a>\r\n      <span class=\"small\">by <a href=\"https://github.com/KBarrow\">KBarrow</a></span></h1>\r\n\r\n    <div class=\"description\">\r\n      SDI Projects\r\n    </div>\r\n\r\n     \r\n      <h2>Authors</h2>\r\n      <p>Kathy Barrow (Kbarrow@fullsail.edu)\r\n<br/>      </p>\r\n    \r\n\r\n    \r\n      <h2>Contact</h2>\r\n      <p>Kathy Barrow (Kbarrow@fullsail.edu)\r\n<br/>      </p>\r\n    <a href=\"http://www.flickr.com/photos/kdittfurth/6732633305/\" \r\n   title=\"My Designs by Kbarrow1974, on Flickr\"><img src=\"http://farm8.staticflickr.com/7021/6732633305_33e6bb9eda_z.jpg\" width=\"640\" \r\n   height=\"414\" alt=\"My Designs\"></a>\r\n\r\n    <h2>Download</h2>\r\n    <p>\r\n      You can download this project in either\r\n      <a href=\"https://github.com/KBarrow/SDI-Projects/zipball/master\">zip</a> or\r\n      <a href=\"https://github.com/KBarrow/SDI-Projects/tarball/master\">tar formats.\r\n    </p>\r\n    <p>You can also clone the project with <a href=\"http://git-scm.com\">Git</a>\r\n      by running:\r\n      <pre>$ git clone git://github.com/KBarrow/SDI-Projects</pre>\r\n    </p>\r\n\r\n    <div class=\"footer\">\r\n      get the source code on GitHub : <a href=\"https://github.com/KBarrow/SDI-Projects\">KBarrow/SDI-Projects</a>\r\n    </div>\r\n\r\n \r\n \r\n  <center>\r\n\r\n<iframe width=\"500\" height=\"415\" src=\"http://www.youtube.com/embed/o-r7SsOp_NM\" \r\nframeborder=\"0\" allowfullscreen></iframe>\r\n</center>\r\n\r\n<br>\r\n\r\n<center>\r\n<iframe width=\"420\" height=\"315\" src=\"http://www.youtube.com/embed/E-SO4bh66yw\" frameborder=\"0\" allowfullscreen></iframe>\r\n</center>\r\n  </div>\r\n\r\n</body>\r\n</html>","tagline":"Assignments","google":"","note":"Don't delete this file! It's used internally to help with page regeneration."}